{
	"translations": {
		"de": {
			"State"			: "Verbindung",
			"Disconnected"	: "Getrennt",
			"Connected"		: "Verbunden",
			"Error"			: "Fehler",
			"On"	:"An",
			"Off"	:"Aus",
			"Yes"	:"Ja",
			"No"	:"Nein",
			"Refresh every"			: "Aktuallisierung alle",
			"Offline check every" 	: "Offline Überprüfung alle",
			"minutes 0=off": "Minuten 0=aus",
			"seconds 0=off": "Sekunden 0=aus",
			"hours 0=off": "Stunden 0=aus",
			"Host": "Host",
           	"Username": "Benutzername",
           	"Password": "Passwort",
           	"Show refresh button":"Schaltfläche \"Aktualisieren\" anzeigen",
           	"Refresh now":"Jetzt aktualisieren",
           	"Refresh":"Aktuallisieren",
           	"Connection ready":"Verbindung bereit",
           	"Host missing or invalid":"Host fehlt oder ist ungültig",
           	"Initializing host missing or invalid":"Initializierungs Host fehlt oder ist ungültig",
           	"Username required":"Benutzername benötigt",
           	"Password required":"Passwort benötigt",

			"External IP-Adress":"Externe IP-Adresse",
			"Download Speed":"Geschwindigkeit Download",
			"Upload Speed":"Geschwindigkeit Upload",
			"Internet State":"Internet Status",
			"Reconnect Internet":"Internet erneut verbinden",
			"Reboot Fritzbox":"Fritzbox Neutarten",
			"WLAN: Guests":"WLAN: Gäste",
			"WLAN: Guests - WPA Key":"WLAN: Gäste - WPA Schlüssel",
			"WLAN: Internal 2.4 Ghz":"WLAN: Intern 2.4 Ghz",
			"WLAN: Internal 5.0 Ghz":"WLAN: Intern 5.0 Ghz",
		   	"Uptime":"Betriebszeit",
		   	"%s Days %s hours %s minutes and %s seconds":"%s Tage %s Stunden %s Minuten und %s sekunden",
		   	"Show answering machine":"Anrufbeantworter anzeigen",
		   	"Show reboot button":"Zeige neu starten",
		   	"Show reconnect button":"Zeige neu Verbinden",
		   	"Show WLAN guest key":"Zeige WLAN Gastschlüssel",
		   	"WLAN guests key":"WLAN Gastschlüssel",
		   	"Enable Wifi2G Action":"Erlaube WLAN 2.4 Ghz Schalten",
		   	"Enable Wifi5G Action":"Erlaube WLAN 5.0 Ghz Schalten",
		   	"Enable WifiGuest Action":"Erlaube Gast WLAN Schalten",
		  
		  	"Show uptime":"Betriebszeit anzeigen",
		  	"Show upload speed":"Upload-Geschwindigkeit anzeigen",
		  	"Show download speed":"Download-Geschwindigkeit anzeigen",
		  	"Show Wifi2G":"WLAN 2.4 Ghz anzeigen",
		  	"Show Wifi5G":"WLAN 5.0 Ghz anzeigen",
		  	"Show Wifi guest":"WLAN Gäste anzeigen",
		  	
		  	"Tam 1":"AB 1",
		  	"Tam 2":"AB 2",
		  	"Tam 3":"AB 3",
		  	"Tam 4":"AB 4",
		  	"Tam 5":"AB 5",
		  	
		  	"Error loading answering machines":"Fehler beim Laden der Anrufbeantworter",
		  	"Answering machines not enabled":"Anrufbeantworter nicht aktiviert"
		}
	}
}